exoedge_simulator/__init__.py
exoedge_simulator/__version__.py
exoedge_simulator/simulator.py
exoedge_simulator/sys_info.py
exoedge_simulator/waves.py
test/__init__.py
test/simulator_test.py
test/test_001_classic_import_style.py
test/test_001_sin_wave.py
test/test_002_architecture.py
test/test_002_echo.py
test/test_003_do_wave.py
test/test_004_report_on_change.py
test/test_007_report_on_change_tolerance.py
exoedge_simulator-21.10.7.dist-info/LICENSE
exoedge_simulator-21.10.7.dist-info/METADATA
exoedge_simulator-21.10.7.dist-info/WHEEL
exoedge_simulator-21.10.7.dist-info/top_level.txt
exoedge_simulator-21.10.7.dist-info/RECORD
